verde/__init__.py
verde/_version.py
verde/_version_generated.py
verde/blockreduce.py
verde/chain.py
verde/coordinates.py
verde/distances.py
verde/io.py
verde/mask.py
verde/model_selection.py
verde/neighbors.py
verde/projections.py
verde/scipygridder.py
verde/spline.py
verde/synthetic.py
verde/trend.py
verde/utils.py
verde/vector.py
verde/base/__init__.py
verde/base/base_classes.py
verde/base/least_squares.py
verde/base/utils.py
verde/datasets/__init__.py
verde/datasets/sample_data.py
verde/datasets/synthetic.py
verde/tests/__init__.py
verde/tests/test_base.py
verde/tests/test_blockreduce.py
verde/tests/test_chain.py
verde/tests/test_coordinates.py
verde/tests/test_datasets.py
verde/tests/test_distances.py
verde/tests/test_io.py
verde/tests/test_mask.py
verde/tests/test_minimal.py
verde/tests/test_model_selection.py
verde/tests/test_neighbors.py
verde/tests/test_projections.py
verde/tests/test_scipy.py
verde/tests/test_spline.py
verde/tests/test_synthetic.py
verde/tests/test_trend.py
verde/tests/test_utils.py
verde/tests/test_vector.py
verde/tests/utils.py
verde/tests/baseline/test_setup_baja_bathymetry.png
verde/tests/baseline/test_setup_california_gps.png
verde/tests/baseline/test_setup_rio_magnetic.png
verde/tests/baseline/test_setup_texas_wind.png
verde-1.8.1.dist-info/LICENSE.txt
verde-1.8.1.dist-info/METADATA
verde-1.8.1.dist-info/WHEEL
verde-1.8.1.dist-info/top_level.txt
verde-1.8.1.dist-info/zip-safe
verde-1.8.1.dist-info/RECORD
