Metadata-Version: 2.1
Name: verde
Version: 1.8.1
Summary: Processing and gridding spatial data, machine-learning style
Home-page: https://github.com/fatiando/verde
Author: The Verde Developers
Author-email: fatiandoaterra@protonmail.com
Maintainer: "Leonardo Uieda"
Maintainer-email: leouieda@gmail.com
License: BSD 3-Clause License
Project-URL: Documentation, https://www.fatiando.org/verde
Project-URL: Release Notes, https://github.com/fatiando/verde/releases
Project-URL: Bug Tracker, https://github.com/fatiando/verde/issues
Project-URL: Source Code, https://github.com/fatiando/verde
Keywords: spatial,geoscience,geophysics,gridding,interpolation
Platform: any
Classifier: Development Status :: 5 - Production/Stable
Classifier: Intended Audience :: Science/Research
Classifier: Intended Audience :: Developers
Classifier: Intended Audience :: Education
Classifier: License :: OSI Approved :: BSD License
Classifier: Natural Language :: English
Classifier: Operating System :: OS Independent
Classifier: Topic :: Scientific/Engineering
Classifier: Topic :: Software Development :: Libraries
Classifier: Programming Language :: Python :: 3 :: Only
Classifier: Programming Language :: Python :: 3.9
Classifier: Programming Language :: Python :: 3.10
Classifier: Programming Language :: Python :: 3.11
Classifier: Programming Language :: Python :: 3.12
Requires-Python: >=3.9
License-File: LICENSE.txt
Requires-Dist: numpy >=1.23
Requires-Dist: scipy >=1.8
Requires-Dist: pandas >=1.4
Requires-Dist: xarray >=2022.03
Requires-Dist: scikit-learn >=1.0
Requires-Dist: pooch >=1.2
Requires-Dist: dask >=2022.01.0
Provides-Extra: fast
Requires-Dist: numba >=0.55 ; extra == 'fast'
Requires-Dist: pykdtree >=1.3 ; extra == 'fast'
